tomplotlib/__init__.py
tomplotlib/tomplotlib.py
tomplotlib/tpl.py
tomplotlib-1.2.3.data/scripts/tomplotlib.py
tomplotlib-1.2.3.data/scripts/tpl.py
tomplotlib-1.2.3.dist-info/METADATA
tomplotlib-1.2.3.dist-info/WHEEL
tomplotlib-1.2.3.dist-info/top_level.txt
tomplotlib-1.2.3.dist-info/RECORD
