Metadata-Version: 2.1
Name: tomplotlib
Version: 1.2.3
Summary: A package which formats matplotlib plots and contains some other useful functions
Home-page: https://github.com/TomGeorge1234/tomplotlib
Author: Tom George
Author-email: tom.george.20@ucl.ac.uk
Classifier: Programming Language :: Python :: 3
Classifier: License :: OSI Approved :: MIT License
Classifier: Operating System :: OS Independent
Requires-Dist: matplotlib
Requires-Dist: numpy
